pushover/__init__.py
pushover/pushover.py
pushover/py.typed
m4rkw_pushover-0.0.5.dist-info/METADATA
m4rkw_pushover-0.0.5.dist-info/WHEEL
m4rkw_pushover-0.0.5.dist-info/top_level.txt
m4rkw_pushover-0.0.5.dist-info/RECORD
