Metadata-Version: 2.4
Name: m4rkw-pushover
Version: 0.0.5
Summary: pushover
Author-email: Your Name <your@email.com>
Requires-Dist: requests
Requires-Dist: types-requests
